[
    {
        "%vlocity_namespace%__ActiveFlg__c": true,
        "%vlocity_namespace%__AttributeCategoryCode__c": "InptAccAndAncllrs",
        "%vlocity_namespace%__AttributeCategoryId__c": {
            "%vlocity_namespace%__Code__c": "InptAccAndAncllrs",
            "VlocityDataPackType": "VlocityMatchingKeyObject",
            "VlocityMatchingRecordSourceKey": "%vlocity_namespace%__AttributeCategory__c/InptAccAndAncllrs",
            "VlocityRecordSObjectType": "%vlocity_namespace%__AttributeCategory__c"
        },
        "%vlocity_namespace%__AttributeCategoryName__c": "Inpatient Accommodations and Ancillaries",
        "%vlocity_namespace%__AttributeGroupType__c": "",
        "%vlocity_namespace%__Code__c": "InpAccandAnc_selection1",
        "%vlocity_namespace%__Configurable__c": true,
        "%vlocity_namespace%__CustomConfigUiTemplate__c": "",
        "%vlocity_namespace%__Description__c": "",
        "%vlocity_namespace%__DisplaySequence__c": 10,
        "%vlocity_namespace%__EffectiveFromDate__c": "",
        "%vlocity_namespace%__EffectiveUntilDate__c": "",
        "%vlocity_namespace%__Filterable__c": true,
        "%vlocity_namespace%__GlobalKey__c": "f58e290f-b696-8f8a-74e0-66f6e54078f1",
        "%vlocity_namespace%__HelpText__c": "",
        "%vlocity_namespace%__IsCloneable__c": true,
        "%vlocity_namespace%__IsEncrypted__c": false,
        "%vlocity_namespace%__IsNotAssetizable__c": false,
        "%vlocity_namespace%__IsPrivate__c": false,
        "%vlocity_namespace%__OwnerId__c": "",
        "%vlocity_namespace%__PicklistId__c": "",
        "%vlocity_namespace%__UniqueNameField__c": "",
        "%vlocity_namespace%__ValueType__c": "Text",
        "%vlocity_namespace%__Value__c": "",
        "%vlocity_namespace%__isDefaultHidden__c": false,
        "Name": "Instructions",
        "VlocityDataPackType": "SObject",
        "VlocityRecordSObjectType": "%vlocity_namespace%__Attribute__c",
        "VlocityRecordSourceKey": "%vlocity_namespace%__Attribute__c/InpAccandAnc_selection1"
    },
    {
        "%vlocity_namespace%__ActiveFlg__c": true,
        "%vlocity_namespace%__AttributeCategoryCode__c": "InptAccAndAncllrs",
        "%vlocity_namespace%__AttributeCategoryId__c": {
            "%vlocity_namespace%__Code__c": "InptAccAndAncllrs",
            "VlocityDataPackType": "VlocityMatchingKeyObject",
            "VlocityMatchingRecordSourceKey": "%vlocity_namespace%__AttributeCategory__c/InptAccAndAncllrs",
            "VlocityRecordSObjectType": "%vlocity_namespace%__AttributeCategory__c"
        },
        "%vlocity_namespace%__AttributeCategoryName__c": "Inpatient Accommodations and Ancillaries",
        "%vlocity_namespace%__AttributeGroupType__c": "In-Network",
        "%vlocity_namespace%__Code__c": "InptAccAndAncllrs_Coins_inn",
        "%vlocity_namespace%__Configurable__c": true,
        "%vlocity_namespace%__CustomConfigUiTemplate__c": "",
        "%vlocity_namespace%__Description__c": "",
        "%vlocity_namespace%__DisplaySequence__c": 20,
        "%vlocity_namespace%__EffectiveFromDate__c": "",
        "%vlocity_namespace%__EffectiveUntilDate__c": "",
        "%vlocity_namespace%__Filterable__c": true,
        "%vlocity_namespace%__GlobalKey__c": "ca6307af-e82b-8111-a5b7-910813a6bb4f",
        "%vlocity_namespace%__HelpText__c": "",
        "%vlocity_namespace%__IsCloneable__c": true,
        "%vlocity_namespace%__IsEncrypted__c": false,
        "%vlocity_namespace%__IsNotAssetizable__c": false,
        "%vlocity_namespace%__IsPrivate__c": false,
        "%vlocity_namespace%__OwnerId__c": "",
        "%vlocity_namespace%__PicklistId__c": "",
        "%vlocity_namespace%__UniqueNameField__c": "",
        "%vlocity_namespace%__ValueType__c": "Text",
        "%vlocity_namespace%__Value__c": "",
        "%vlocity_namespace%__isDefaultHidden__c": false,
        "Name": "Covered at",
        "VlocityDataPackType": "SObject",
        "VlocityRecordSObjectType": "%vlocity_namespace%__Attribute__c",
        "VlocityRecordSourceKey": "%vlocity_namespace%__Attribute__c/InptAccAndAncllrs_Coins_inn"
    },
    {
        "%vlocity_namespace%__ActiveFlg__c": true,
        "%vlocity_namespace%__AttributeCategoryCode__c": "InptAccAndAncllrs",
        "%vlocity_namespace%__AttributeCategoryId__c": {
            "%vlocity_namespace%__Code__c": "InptAccAndAncllrs",
            "VlocityDataPackType": "VlocityMatchingKeyObject",
            "VlocityMatchingRecordSourceKey": "%vlocity_namespace%__AttributeCategory__c/InptAccAndAncllrs",
            "VlocityRecordSObjectType": "%vlocity_namespace%__AttributeCategory__c"
        },
        "%vlocity_namespace%__AttributeCategoryName__c": "Inpatient Accommodations and Ancillaries",
        "%vlocity_namespace%__AttributeGroupType__c": "Out-Of-Network",
        "%vlocity_namespace%__Code__c": "InptAccAndAncllrs_Coins_oon",
        "%vlocity_namespace%__Configurable__c": true,
        "%vlocity_namespace%__CustomConfigUiTemplate__c": "",
        "%vlocity_namespace%__Description__c": "",
        "%vlocity_namespace%__DisplaySequence__c": 60,
        "%vlocity_namespace%__EffectiveFromDate__c": "",
        "%vlocity_namespace%__EffectiveUntilDate__c": "",
        "%vlocity_namespace%__Filterable__c": true,
        "%vlocity_namespace%__GlobalKey__c": "206c390a-e129-d6b8-a0e9-0b8d8b2db3c9",
        "%vlocity_namespace%__HelpText__c": "",
        "%vlocity_namespace%__IsCloneable__c": true,
        "%vlocity_namespace%__IsEncrypted__c": false,
        "%vlocity_namespace%__IsNotAssetizable__c": false,
        "%vlocity_namespace%__IsPrivate__c": false,
        "%vlocity_namespace%__OwnerId__c": "",
        "%vlocity_namespace%__PicklistId__c": "",
        "%vlocity_namespace%__UniqueNameField__c": "",
        "%vlocity_namespace%__ValueType__c": "Text",
        "%vlocity_namespace%__Value__c": "",
        "%vlocity_namespace%__isDefaultHidden__c": false,
        "Name": "Covered at",
        "VlocityDataPackType": "SObject",
        "VlocityRecordSObjectType": "%vlocity_namespace%__Attribute__c",
        "VlocityRecordSourceKey": "%vlocity_namespace%__Attribute__c/InptAccAndAncllrs_Coins_oon"
    },
    {
        "%vlocity_namespace%__ActiveFlg__c": true,
        "%vlocity_namespace%__AttributeCategoryCode__c": "InptAccAndAncllrs",
        "%vlocity_namespace%__AttributeCategoryId__c": {
            "%vlocity_namespace%__Code__c": "InptAccAndAncllrs",
            "VlocityDataPackType": "VlocityMatchingKeyObject",
            "VlocityMatchingRecordSourceKey": "%vlocity_namespace%__AttributeCategory__c/InptAccAndAncllrs",
            "VlocityRecordSObjectType": "%vlocity_namespace%__AttributeCategory__c"
        },
        "%vlocity_namespace%__AttributeCategoryName__c": "Inpatient Accommodations and Ancillaries",
        "%vlocity_namespace%__AttributeGroupType__c": "In-Network",
        "%vlocity_namespace%__Code__c": "InptAccAndAncllrs_Cpy_inn",
        "%vlocity_namespace%__Configurable__c": true,
        "%vlocity_namespace%__CustomConfigUiTemplate__c": "",
        "%vlocity_namespace%__Description__c": "",
        "%vlocity_namespace%__DisplaySequence__c": 40,
        "%vlocity_namespace%__EffectiveFromDate__c": "",
        "%vlocity_namespace%__EffectiveUntilDate__c": "",
        "%vlocity_namespace%__Filterable__c": true,
        "%vlocity_namespace%__GlobalKey__c": "40f3d190-bf85-baab-5a2b-1237eb18a55a",
        "%vlocity_namespace%__HelpText__c": "",
        "%vlocity_namespace%__IsCloneable__c": true,
        "%vlocity_namespace%__IsEncrypted__c": false,
        "%vlocity_namespace%__IsNotAssetizable__c": false,
        "%vlocity_namespace%__IsPrivate__c": false,
        "%vlocity_namespace%__OwnerId__c": "",
        "%vlocity_namespace%__PicklistId__c": "",
        "%vlocity_namespace%__UniqueNameField__c": "",
        "%vlocity_namespace%__ValueType__c": "Text",
        "%vlocity_namespace%__Value__c": "",
        "%vlocity_namespace%__isDefaultHidden__c": false,
        "Name": "Copay",
        "VlocityDataPackType": "SObject",
        "VlocityRecordSObjectType": "%vlocity_namespace%__Attribute__c",
        "VlocityRecordSourceKey": "%vlocity_namespace%__Attribute__c/InptAccAndAncllrs_Cpy_inn"
    },
    {
        "%vlocity_namespace%__ActiveFlg__c": true,
        "%vlocity_namespace%__AttributeCategoryCode__c": "InptAccAndAncllrs",
        "%vlocity_namespace%__AttributeCategoryId__c": {
            "%vlocity_namespace%__Code__c": "InptAccAndAncllrs",
            "VlocityDataPackType": "VlocityMatchingKeyObject",
            "VlocityMatchingRecordSourceKey": "%vlocity_namespace%__AttributeCategory__c/InptAccAndAncllrs",
            "VlocityRecordSObjectType": "%vlocity_namespace%__AttributeCategory__c"
        },
        "%vlocity_namespace%__AttributeCategoryName__c": "Inpatient Accommodations and Ancillaries",
        "%vlocity_namespace%__AttributeGroupType__c": "Out-Of-Network",
        "%vlocity_namespace%__Code__c": "InptAccAndAncllrs_Cpy_oon",
        "%vlocity_namespace%__Configurable__c": true,
        "%vlocity_namespace%__CustomConfigUiTemplate__c": "",
        "%vlocity_namespace%__Description__c": "",
        "%vlocity_namespace%__DisplaySequence__c": 80,
        "%vlocity_namespace%__EffectiveFromDate__c": "",
        "%vlocity_namespace%__EffectiveUntilDate__c": "",
        "%vlocity_namespace%__Filterable__c": true,
        "%vlocity_namespace%__GlobalKey__c": "9b7f84fa-9b37-c278-b615-febad7c46cab",
        "%vlocity_namespace%__HelpText__c": "",
        "%vlocity_namespace%__IsCloneable__c": true,
        "%vlocity_namespace%__IsEncrypted__c": false,
        "%vlocity_namespace%__IsNotAssetizable__c": false,
        "%vlocity_namespace%__IsPrivate__c": false,
        "%vlocity_namespace%__OwnerId__c": "",
        "%vlocity_namespace%__PicklistId__c": "",
        "%vlocity_namespace%__UniqueNameField__c": "",
        "%vlocity_namespace%__ValueType__c": "Text",
        "%vlocity_namespace%__Value__c": "",
        "%vlocity_namespace%__isDefaultHidden__c": false,
        "Name": "Copay",
        "VlocityDataPackType": "SObject",
        "VlocityRecordSObjectType": "%vlocity_namespace%__Attribute__c",
        "VlocityRecordSourceKey": "%vlocity_namespace%__Attribute__c/InptAccAndAncllrs_Cpy_oon"
    },
    {
        "%vlocity_namespace%__ActiveFlg__c": true,
        "%vlocity_namespace%__AttributeCategoryCode__c": "InptAccAndAncllrs",
        "%vlocity_namespace%__AttributeCategoryId__c": {
            "%vlocity_namespace%__Code__c": "InptAccAndAncllrs",
            "VlocityDataPackType": "VlocityMatchingKeyObject",
            "VlocityMatchingRecordSourceKey": "%vlocity_namespace%__AttributeCategory__c/InptAccAndAncllrs",
            "VlocityRecordSObjectType": "%vlocity_namespace%__AttributeCategory__c"
        },
        "%vlocity_namespace%__AttributeCategoryName__c": "Inpatient Accommodations and Ancillaries",
        "%vlocity_namespace%__AttributeGroupType__c": "In-Network",
        "%vlocity_namespace%__Code__c": "InptAccAndAncllrs_Ded_inn",
        "%vlocity_namespace%__Configurable__c": true,
        "%vlocity_namespace%__CustomConfigUiTemplate__c": "",
        "%vlocity_namespace%__Description__c": "",
        "%vlocity_namespace%__DisplaySequence__c": 30,
        "%vlocity_namespace%__EffectiveFromDate__c": "",
        "%vlocity_namespace%__EffectiveUntilDate__c": "",
        "%vlocity_namespace%__Filterable__c": true,
        "%vlocity_namespace%__GlobalKey__c": "dd2ebcdb-e226-0fb3-4c14-65b88b5f138a",
        "%vlocity_namespace%__HelpText__c": "",
        "%vlocity_namespace%__IsCloneable__c": true,
        "%vlocity_namespace%__IsEncrypted__c": false,
        "%vlocity_namespace%__IsNotAssetizable__c": false,
        "%vlocity_namespace%__IsPrivate__c": false,
        "%vlocity_namespace%__OwnerId__c": "",
        "%vlocity_namespace%__PicklistId__c": "",
        "%vlocity_namespace%__UniqueNameField__c": "",
        "%vlocity_namespace%__ValueType__c": "Text",
        "%vlocity_namespace%__Value__c": "",
        "%vlocity_namespace%__isDefaultHidden__c": false,
        "Name": "Deductible",
        "VlocityDataPackType": "SObject",
        "VlocityRecordSObjectType": "%vlocity_namespace%__Attribute__c",
        "VlocityRecordSourceKey": "%vlocity_namespace%__Attribute__c/InptAccAndAncllrs_Ded_inn"
    },
    {
        "%vlocity_namespace%__ActiveFlg__c": true,
        "%vlocity_namespace%__AttributeCategoryCode__c": "InptAccAndAncllrs",
        "%vlocity_namespace%__AttributeCategoryId__c": {
            "%vlocity_namespace%__Code__c": "InptAccAndAncllrs",
            "VlocityDataPackType": "VlocityMatchingKeyObject",
            "VlocityMatchingRecordSourceKey": "%vlocity_namespace%__AttributeCategory__c/InptAccAndAncllrs",
            "VlocityRecordSObjectType": "%vlocity_namespace%__AttributeCategory__c"
        },
        "%vlocity_namespace%__AttributeCategoryName__c": "Inpatient Accommodations and Ancillaries",
        "%vlocity_namespace%__AttributeGroupType__c": "Out-Of-Network",
        "%vlocity_namespace%__Code__c": "InptAccAndAncllrs_Ded_oon",
        "%vlocity_namespace%__Configurable__c": true,
        "%vlocity_namespace%__CustomConfigUiTemplate__c": "",
        "%vlocity_namespace%__Description__c": "",
        "%vlocity_namespace%__DisplaySequence__c": 70,
        "%vlocity_namespace%__EffectiveFromDate__c": "",
        "%vlocity_namespace%__EffectiveUntilDate__c": "",
        "%vlocity_namespace%__Filterable__c": true,
        "%vlocity_namespace%__GlobalKey__c": "e68aca8e-a26b-47ad-20cd-85c55a21a9fb",
        "%vlocity_namespace%__HelpText__c": "",
        "%vlocity_namespace%__IsCloneable__c": true,
        "%vlocity_namespace%__IsEncrypted__c": false,
        "%vlocity_namespace%__IsNotAssetizable__c": false,
        "%vlocity_namespace%__IsPrivate__c": false,
        "%vlocity_namespace%__OwnerId__c": "",
        "%vlocity_namespace%__PicklistId__c": "",
        "%vlocity_namespace%__UniqueNameField__c": "",
        "%vlocity_namespace%__ValueType__c": "Text",
        "%vlocity_namespace%__Value__c": "",
        "%vlocity_namespace%__isDefaultHidden__c": false,
        "Name": "Deducitble",
        "VlocityDataPackType": "SObject",
        "VlocityRecordSObjectType": "%vlocity_namespace%__Attribute__c",
        "VlocityRecordSourceKey": "%vlocity_namespace%__Attribute__c/InptAccAndAncllrs_Ded_oon"
    },
    {
        "%vlocity_namespace%__ActiveFlg__c": true,
        "%vlocity_namespace%__AttributeCategoryCode__c": "InptAccAndAncllrs",
        "%vlocity_namespace%__AttributeCategoryId__c": {
            "%vlocity_namespace%__Code__c": "InptAccAndAncllrs",
            "VlocityDataPackType": "VlocityMatchingKeyObject",
            "VlocityMatchingRecordSourceKey": "%vlocity_namespace%__AttributeCategory__c/InptAccAndAncllrs",
            "VlocityRecordSObjectType": "%vlocity_namespace%__AttributeCategory__c"
        },
        "%vlocity_namespace%__AttributeCategoryName__c": "Inpatient Accommodations and Ancillaries",
        "%vlocity_namespace%__AttributeGroupType__c": "",
        "%vlocity_namespace%__Code__c": "InptAccAndAncllrs_Instrctn",
        "%vlocity_namespace%__Configurable__c": true,
        "%vlocity_namespace%__CustomConfigUiTemplate__c": "",
        "%vlocity_namespace%__Description__c": "",
        "%vlocity_namespace%__DisplaySequence__c": 90,
        "%vlocity_namespace%__EffectiveFromDate__c": "",
        "%vlocity_namespace%__EffectiveUntilDate__c": "",
        "%vlocity_namespace%__Filterable__c": true,
        "%vlocity_namespace%__GlobalKey__c": "9c7d7cf7-21ca-b8f9-8f77-8bbcd90aa698",
        "%vlocity_namespace%__HelpText__c": "",
        "%vlocity_namespace%__IsCloneable__c": true,
        "%vlocity_namespace%__IsEncrypted__c": false,
        "%vlocity_namespace%__IsNotAssetizable__c": false,
        "%vlocity_namespace%__IsPrivate__c": false,
        "%vlocity_namespace%__OwnerId__c": "",
        "%vlocity_namespace%__PicklistId__c": "",
        "%vlocity_namespace%__UniqueNameField__c": "",
        "%vlocity_namespace%__ValueType__c": "Text",
        "%vlocity_namespace%__Value__c": "",
        "%vlocity_namespace%__isDefaultHidden__c": false,
        "Name": "Instructions",
        "VlocityDataPackType": "SObject",
        "VlocityRecordSObjectType": "%vlocity_namespace%__Attribute__c",
        "VlocityRecordSourceKey": "%vlocity_namespace%__Attribute__c/InptAccAndAncllrs_Instrctn"
    },
    {
        "%vlocity_namespace%__ActiveFlg__c": true,
        "%vlocity_namespace%__AttributeCategoryCode__c": "InptAccAndAncllrs",
        "%vlocity_namespace%__AttributeCategoryId__c": {
            "%vlocity_namespace%__Code__c": "InptAccAndAncllrs",
            "VlocityDataPackType": "VlocityMatchingKeyObject",
            "VlocityMatchingRecordSourceKey": "%vlocity_namespace%__AttributeCategory__c/InptAccAndAncllrs",
            "VlocityRecordSObjectType": "%vlocity_namespace%__AttributeCategory__c"
        },
        "%vlocity_namespace%__AttributeCategoryName__c": "Inpatient Accommodations and Ancillaries",
        "%vlocity_namespace%__AttributeGroupType__c": "In-Network",
        "%vlocity_namespace%__Code__c": "InptAccAndAncllrs_covered_inn",
        "%vlocity_namespace%__Configurable__c": true,
        "%vlocity_namespace%__CustomConfigUiTemplate__c": "",
        "%vlocity_namespace%__Description__c": "",
        "%vlocity_namespace%__DisplaySequence__c": 10,
        "%vlocity_namespace%__EffectiveFromDate__c": "",
        "%vlocity_namespace%__EffectiveUntilDate__c": "",
        "%vlocity_namespace%__Filterable__c": true,
        "%vlocity_namespace%__GlobalKey__c": "60c7d181-7f53-d6c9-51d6-e2d254c5e9f3",
        "%vlocity_namespace%__HelpText__c": "",
        "%vlocity_namespace%__IsCloneable__c": true,
        "%vlocity_namespace%__IsEncrypted__c": false,
        "%vlocity_namespace%__IsNotAssetizable__c": false,
        "%vlocity_namespace%__IsPrivate__c": false,
        "%vlocity_namespace%__OwnerId__c": "",
        "%vlocity_namespace%__PicklistId__c": "",
        "%vlocity_namespace%__UniqueNameField__c": "",
        "%vlocity_namespace%__ValueType__c": "Text",
        "%vlocity_namespace%__Value__c": "",
        "%vlocity_namespace%__isDefaultHidden__c": false,
        "Name": "Covered",
        "VlocityDataPackType": "SObject",
        "VlocityRecordSObjectType": "%vlocity_namespace%__Attribute__c",
        "VlocityRecordSourceKey": "%vlocity_namespace%__Attribute__c/InptAccAndAncllrs_covered_inn"
    },
    {
        "%vlocity_namespace%__ActiveFlg__c": true,
        "%vlocity_namespace%__AttributeCategoryCode__c": "InptAccAndAncllrs",
        "%vlocity_namespace%__AttributeCategoryId__c": {
            "%vlocity_namespace%__Code__c": "InptAccAndAncllrs",
            "VlocityDataPackType": "VlocityMatchingKeyObject",
            "VlocityMatchingRecordSourceKey": "%vlocity_namespace%__AttributeCategory__c/InptAccAndAncllrs",
            "VlocityRecordSObjectType": "%vlocity_namespace%__AttributeCategory__c"
        },
        "%vlocity_namespace%__AttributeCategoryName__c": "Inpatient Accommodations and Ancillaries",
        "%vlocity_namespace%__AttributeGroupType__c": "Out-Of-Network",
        "%vlocity_namespace%__Code__c": "InptAccAndAncllrs_covered_oon",
        "%vlocity_namespace%__Configurable__c": true,
        "%vlocity_namespace%__CustomConfigUiTemplate__c": "",
        "%vlocity_namespace%__Description__c": "",
        "%vlocity_namespace%__DisplaySequence__c": 5,
        "%vlocity_namespace%__EffectiveFromDate__c": "",
        "%vlocity_namespace%__EffectiveUntilDate__c": "",
        "%vlocity_namespace%__Filterable__c": true,
        "%vlocity_namespace%__GlobalKey__c": "abe681d4-beb5-2e5e-a6cf-d7622b83f8cd",
        "%vlocity_namespace%__HelpText__c": "",
        "%vlocity_namespace%__IsCloneable__c": true,
        "%vlocity_namespace%__IsEncrypted__c": false,
        "%vlocity_namespace%__IsNotAssetizable__c": false,
        "%vlocity_namespace%__IsPrivate__c": false,
        "%vlocity_namespace%__OwnerId__c": "",
        "%vlocity_namespace%__PicklistId__c": "",
        "%vlocity_namespace%__UniqueNameField__c": "",
        "%vlocity_namespace%__ValueType__c": "Text",
        "%vlocity_namespace%__Value__c": "",
        "%vlocity_namespace%__isDefaultHidden__c": false,
        "Name": "Covered",
        "VlocityDataPackType": "SObject",
        "VlocityRecordSObjectType": "%vlocity_namespace%__Attribute__c",
        "VlocityRecordSourceKey": "%vlocity_namespace%__Attribute__c/InptAccAndAncllrs_covered_oon"
    }
]