[
    {
        "%vlocity_namespace%__ActiveFlg__c": true,
        "%vlocity_namespace%__AttributeCategoryCode__c": "MntlHlthOutptProf",
        "%vlocity_namespace%__AttributeCategoryId__c": {
            "%vlocity_namespace%__Code__c": "MntlHlthOutptProf",
            "VlocityDataPackType": "VlocityMatchingKeyObject",
            "VlocityMatchingRecordSourceKey": "%vlocity_namespace%__AttributeCategory__c/MntlHlthOutptProf",
            "VlocityRecordSObjectType": "%vlocity_namespace%__AttributeCategory__c"
        },
        "%vlocity_namespace%__AttributeCategoryName__c": "Mental Health - Outpatient Professional",
        "%vlocity_namespace%__AttributeGroupType__c": "In-Network",
        "%vlocity_namespace%__Code__c": "MntlHlthOutptProf_Coins_inn",
        "%vlocity_namespace%__Configurable__c": true,
        "%vlocity_namespace%__CustomConfigUiTemplate__c": "",
        "%vlocity_namespace%__Description__c": "",
        "%vlocity_namespace%__DisplaySequence__c": 20,
        "%vlocity_namespace%__EffectiveFromDate__c": "",
        "%vlocity_namespace%__EffectiveUntilDate__c": "",
        "%vlocity_namespace%__Filterable__c": true,
        "%vlocity_namespace%__GlobalKey__c": "f409c453-2166-0cb1-5e24-bf668dd944f4",
        "%vlocity_namespace%__HelpText__c": "",
        "%vlocity_namespace%__IsCloneable__c": true,
        "%vlocity_namespace%__IsEncrypted__c": false,
        "%vlocity_namespace%__IsNotAssetizable__c": false,
        "%vlocity_namespace%__IsPrivate__c": false,
        "%vlocity_namespace%__OwnerId__c": "",
        "%vlocity_namespace%__PicklistId__c": "",
        "%vlocity_namespace%__UniqueNameField__c": "",
        "%vlocity_namespace%__ValueType__c": "Text",
        "%vlocity_namespace%__Value__c": "",
        "%vlocity_namespace%__isDefaultHidden__c": false,
        "Name": "Covered at",
        "VlocityDataPackType": "SObject",
        "VlocityRecordSObjectType": "%vlocity_namespace%__Attribute__c",
        "VlocityRecordSourceKey": "%vlocity_namespace%__Attribute__c/MntlHlthOutptProf_Coins_inn"
    },
    {
        "%vlocity_namespace%__ActiveFlg__c": true,
        "%vlocity_namespace%__AttributeCategoryCode__c": "MntlHlthOutptProf",
        "%vlocity_namespace%__AttributeCategoryId__c": {
            "%vlocity_namespace%__Code__c": "MntlHlthOutptProf",
            "VlocityDataPackType": "VlocityMatchingKeyObject",
            "VlocityMatchingRecordSourceKey": "%vlocity_namespace%__AttributeCategory__c/MntlHlthOutptProf",
            "VlocityRecordSObjectType": "%vlocity_namespace%__AttributeCategory__c"
        },
        "%vlocity_namespace%__AttributeCategoryName__c": "Mental Health - Outpatient Professional",
        "%vlocity_namespace%__AttributeGroupType__c": "Out-Of-Network",
        "%vlocity_namespace%__Code__c": "MntlHlthOutptProf_Coins_oon",
        "%vlocity_namespace%__Configurable__c": true,
        "%vlocity_namespace%__CustomConfigUiTemplate__c": "",
        "%vlocity_namespace%__Description__c": "",
        "%vlocity_namespace%__DisplaySequence__c": 60,
        "%vlocity_namespace%__EffectiveFromDate__c": "",
        "%vlocity_namespace%__EffectiveUntilDate__c": "",
        "%vlocity_namespace%__Filterable__c": true,
        "%vlocity_namespace%__GlobalKey__c": "d019ae71-99cc-7c22-06d3-c06fe2000719",
        "%vlocity_namespace%__HelpText__c": "",
        "%vlocity_namespace%__IsCloneable__c": true,
        "%vlocity_namespace%__IsEncrypted__c": false,
        "%vlocity_namespace%__IsNotAssetizable__c": false,
        "%vlocity_namespace%__IsPrivate__c": false,
        "%vlocity_namespace%__OwnerId__c": "",
        "%vlocity_namespace%__PicklistId__c": "",
        "%vlocity_namespace%__UniqueNameField__c": "",
        "%vlocity_namespace%__ValueType__c": "Text",
        "%vlocity_namespace%__Value__c": "",
        "%vlocity_namespace%__isDefaultHidden__c": false,
        "Name": "Covered at",
        "VlocityDataPackType": "SObject",
        "VlocityRecordSObjectType": "%vlocity_namespace%__Attribute__c",
        "VlocityRecordSourceKey": "%vlocity_namespace%__Attribute__c/MntlHlthOutptProf_Coins_oon"
    },
    {
        "%vlocity_namespace%__ActiveFlg__c": true,
        "%vlocity_namespace%__AttributeCategoryCode__c": "MntlHlthOutptProf",
        "%vlocity_namespace%__AttributeCategoryId__c": {
            "%vlocity_namespace%__Code__c": "MntlHlthOutptProf",
            "VlocityDataPackType": "VlocityMatchingKeyObject",
            "VlocityMatchingRecordSourceKey": "%vlocity_namespace%__AttributeCategory__c/MntlHlthOutptProf",
            "VlocityRecordSObjectType": "%vlocity_namespace%__AttributeCategory__c"
        },
        "%vlocity_namespace%__AttributeCategoryName__c": "Mental Health - Outpatient Professional",
        "%vlocity_namespace%__AttributeGroupType__c": "In-Network",
        "%vlocity_namespace%__Code__c": "MntlHlthOutptProf_Cpy_inn",
        "%vlocity_namespace%__Configurable__c": true,
        "%vlocity_namespace%__CustomConfigUiTemplate__c": "",
        "%vlocity_namespace%__Description__c": "",
        "%vlocity_namespace%__DisplaySequence__c": 40,
        "%vlocity_namespace%__EffectiveFromDate__c": "",
        "%vlocity_namespace%__EffectiveUntilDate__c": "",
        "%vlocity_namespace%__Filterable__c": true,
        "%vlocity_namespace%__GlobalKey__c": "a3ee5854-a485-5637-e654-1cd4d69e7901",
        "%vlocity_namespace%__HelpText__c": "",
        "%vlocity_namespace%__IsCloneable__c": true,
        "%vlocity_namespace%__IsEncrypted__c": false,
        "%vlocity_namespace%__IsNotAssetizable__c": false,
        "%vlocity_namespace%__IsPrivate__c": false,
        "%vlocity_namespace%__OwnerId__c": "",
        "%vlocity_namespace%__PicklistId__c": "",
        "%vlocity_namespace%__UniqueNameField__c": "",
        "%vlocity_namespace%__ValueType__c": "Text",
        "%vlocity_namespace%__Value__c": "",
        "%vlocity_namespace%__isDefaultHidden__c": false,
        "Name": "Copay",
        "VlocityDataPackType": "SObject",
        "VlocityRecordSObjectType": "%vlocity_namespace%__Attribute__c",
        "VlocityRecordSourceKey": "%vlocity_namespace%__Attribute__c/MntlHlthOutptProf_Cpy_inn"
    },
    {
        "%vlocity_namespace%__ActiveFlg__c": true,
        "%vlocity_namespace%__AttributeCategoryCode__c": "MntlHlthOutptProf",
        "%vlocity_namespace%__AttributeCategoryId__c": {
            "%vlocity_namespace%__Code__c": "MntlHlthOutptProf",
            "VlocityDataPackType": "VlocityMatchingKeyObject",
            "VlocityMatchingRecordSourceKey": "%vlocity_namespace%__AttributeCategory__c/MntlHlthOutptProf",
            "VlocityRecordSObjectType": "%vlocity_namespace%__AttributeCategory__c"
        },
        "%vlocity_namespace%__AttributeCategoryName__c": "Mental Health - Outpatient Professional",
        "%vlocity_namespace%__AttributeGroupType__c": "Out-Of-Network",
        "%vlocity_namespace%__Code__c": "MntlHlthOutptProf_Cpy_oon",
        "%vlocity_namespace%__Configurable__c": true,
        "%vlocity_namespace%__CustomConfigUiTemplate__c": "",
        "%vlocity_namespace%__Description__c": "",
        "%vlocity_namespace%__DisplaySequence__c": 80,
        "%vlocity_namespace%__EffectiveFromDate__c": "",
        "%vlocity_namespace%__EffectiveUntilDate__c": "",
        "%vlocity_namespace%__Filterable__c": true,
        "%vlocity_namespace%__GlobalKey__c": "430fbad9-c68c-ce38-b125-c9df5fbf6c0d",
        "%vlocity_namespace%__HelpText__c": "",
        "%vlocity_namespace%__IsCloneable__c": true,
        "%vlocity_namespace%__IsEncrypted__c": false,
        "%vlocity_namespace%__IsNotAssetizable__c": false,
        "%vlocity_namespace%__IsPrivate__c": false,
        "%vlocity_namespace%__OwnerId__c": "",
        "%vlocity_namespace%__PicklistId__c": "",
        "%vlocity_namespace%__UniqueNameField__c": "",
        "%vlocity_namespace%__ValueType__c": "Text",
        "%vlocity_namespace%__Value__c": "",
        "%vlocity_namespace%__isDefaultHidden__c": false,
        "Name": "Copay",
        "VlocityDataPackType": "SObject",
        "VlocityRecordSObjectType": "%vlocity_namespace%__Attribute__c",
        "VlocityRecordSourceKey": "%vlocity_namespace%__Attribute__c/MntlHlthOutptProf_Cpy_oon"
    },
    {
        "%vlocity_namespace%__ActiveFlg__c": true,
        "%vlocity_namespace%__AttributeCategoryCode__c": "MntlHlthOutptProf",
        "%vlocity_namespace%__AttributeCategoryId__c": {
            "%vlocity_namespace%__Code__c": "MntlHlthOutptProf",
            "VlocityDataPackType": "VlocityMatchingKeyObject",
            "VlocityMatchingRecordSourceKey": "%vlocity_namespace%__AttributeCategory__c/MntlHlthOutptProf",
            "VlocityRecordSObjectType": "%vlocity_namespace%__AttributeCategory__c"
        },
        "%vlocity_namespace%__AttributeCategoryName__c": "Mental Health - Outpatient Professional",
        "%vlocity_namespace%__AttributeGroupType__c": "In-Network",
        "%vlocity_namespace%__Code__c": "MntlHlthOutptProf_Ded_inn",
        "%vlocity_namespace%__Configurable__c": true,
        "%vlocity_namespace%__CustomConfigUiTemplate__c": "",
        "%vlocity_namespace%__Description__c": "",
        "%vlocity_namespace%__DisplaySequence__c": 30,
        "%vlocity_namespace%__EffectiveFromDate__c": "",
        "%vlocity_namespace%__EffectiveUntilDate__c": "",
        "%vlocity_namespace%__Filterable__c": true,
        "%vlocity_namespace%__GlobalKey__c": "66b6482c-a1a7-8fc7-a6af-1dbcc2b1f6b7",
        "%vlocity_namespace%__HelpText__c": "",
        "%vlocity_namespace%__IsCloneable__c": true,
        "%vlocity_namespace%__IsEncrypted__c": false,
        "%vlocity_namespace%__IsNotAssetizable__c": false,
        "%vlocity_namespace%__IsPrivate__c": false,
        "%vlocity_namespace%__OwnerId__c": "",
        "%vlocity_namespace%__PicklistId__c": "",
        "%vlocity_namespace%__UniqueNameField__c": "",
        "%vlocity_namespace%__ValueType__c": "Text",
        "%vlocity_namespace%__Value__c": "",
        "%vlocity_namespace%__isDefaultHidden__c": false,
        "Name": "Deductible",
        "VlocityDataPackType": "SObject",
        "VlocityRecordSObjectType": "%vlocity_namespace%__Attribute__c",
        "VlocityRecordSourceKey": "%vlocity_namespace%__Attribute__c/MntlHlthOutptProf_Ded_inn"
    },
    {
        "%vlocity_namespace%__ActiveFlg__c": true,
        "%vlocity_namespace%__AttributeCategoryCode__c": "MntlHlthOutptProf",
        "%vlocity_namespace%__AttributeCategoryId__c": {
            "%vlocity_namespace%__Code__c": "MntlHlthOutptProf",
            "VlocityDataPackType": "VlocityMatchingKeyObject",
            "VlocityMatchingRecordSourceKey": "%vlocity_namespace%__AttributeCategory__c/MntlHlthOutptProf",
            "VlocityRecordSObjectType": "%vlocity_namespace%__AttributeCategory__c"
        },
        "%vlocity_namespace%__AttributeCategoryName__c": "Mental Health - Outpatient Professional",
        "%vlocity_namespace%__AttributeGroupType__c": "Out-Of-Network",
        "%vlocity_namespace%__Code__c": "MntlHlthOutptProf_Ded_oon",
        "%vlocity_namespace%__Configurable__c": true,
        "%vlocity_namespace%__CustomConfigUiTemplate__c": "",
        "%vlocity_namespace%__Description__c": "",
        "%vlocity_namespace%__DisplaySequence__c": 70,
        "%vlocity_namespace%__EffectiveFromDate__c": "",
        "%vlocity_namespace%__EffectiveUntilDate__c": "",
        "%vlocity_namespace%__Filterable__c": true,
        "%vlocity_namespace%__GlobalKey__c": "39b9361a-e196-fd07-5774-e23ede06d4ee",
        "%vlocity_namespace%__HelpText__c": "",
        "%vlocity_namespace%__IsCloneable__c": true,
        "%vlocity_namespace%__IsEncrypted__c": false,
        "%vlocity_namespace%__IsNotAssetizable__c": false,
        "%vlocity_namespace%__IsPrivate__c": false,
        "%vlocity_namespace%__OwnerId__c": "",
        "%vlocity_namespace%__PicklistId__c": "",
        "%vlocity_namespace%__UniqueNameField__c": "",
        "%vlocity_namespace%__ValueType__c": "Text",
        "%vlocity_namespace%__Value__c": "",
        "%vlocity_namespace%__isDefaultHidden__c": false,
        "Name": "Deductible",
        "VlocityDataPackType": "SObject",
        "VlocityRecordSObjectType": "%vlocity_namespace%__Attribute__c",
        "VlocityRecordSourceKey": "%vlocity_namespace%__Attribute__c/MntlHlthOutptProf_Ded_oon"
    },
    {
        "%vlocity_namespace%__ActiveFlg__c": true,
        "%vlocity_namespace%__AttributeCategoryCode__c": "MntlHlthOutptProf",
        "%vlocity_namespace%__AttributeCategoryId__c": {
            "%vlocity_namespace%__Code__c": "MntlHlthOutptProf",
            "VlocityDataPackType": "VlocityMatchingKeyObject",
            "VlocityMatchingRecordSourceKey": "%vlocity_namespace%__AttributeCategory__c/MntlHlthOutptProf",
            "VlocityRecordSObjectType": "%vlocity_namespace%__AttributeCategory__c"
        },
        "%vlocity_namespace%__AttributeCategoryName__c": "Mental Health - Outpatient Professional",
        "%vlocity_namespace%__AttributeGroupType__c": "",
        "%vlocity_namespace%__Code__c": "MntlHlthOutptProf_Instrctn2",
        "%vlocity_namespace%__Configurable__c": true,
        "%vlocity_namespace%__CustomConfigUiTemplate__c": "",
        "%vlocity_namespace%__Description__c": "",
        "%vlocity_namespace%__DisplaySequence__c": 12,
        "%vlocity_namespace%__EffectiveFromDate__c": "",
        "%vlocity_namespace%__EffectiveUntilDate__c": "",
        "%vlocity_namespace%__Filterable__c": true,
        "%vlocity_namespace%__GlobalKey__c": "1150535b-ce9c-049d-3ee1-ef97e5ede533",
        "%vlocity_namespace%__HelpText__c": "",
        "%vlocity_namespace%__IsCloneable__c": true,
        "%vlocity_namespace%__IsEncrypted__c": false,
        "%vlocity_namespace%__IsNotAssetizable__c": false,
        "%vlocity_namespace%__IsPrivate__c": false,
        "%vlocity_namespace%__OwnerId__c": "",
        "%vlocity_namespace%__PicklistId__c": "",
        "%vlocity_namespace%__UniqueNameField__c": "",
        "%vlocity_namespace%__ValueType__c": "Text",
        "%vlocity_namespace%__Value__c": "",
        "%vlocity_namespace%__isDefaultHidden__c": false,
        "Name": "Instruction",
        "VlocityDataPackType": "SObject",
        "VlocityRecordSObjectType": "%vlocity_namespace%__Attribute__c",
        "VlocityRecordSourceKey": "%vlocity_namespace%__Attribute__c/MntlHlthOutptProf_Instrctn2"
    },
    {
        "%vlocity_namespace%__ActiveFlg__c": true,
        "%vlocity_namespace%__AttributeCategoryCode__c": "MntlHlthOutptProf",
        "%vlocity_namespace%__AttributeCategoryId__c": {
            "%vlocity_namespace%__Code__c": "MntlHlthOutptProf",
            "VlocityDataPackType": "VlocityMatchingKeyObject",
            "VlocityMatchingRecordSourceKey": "%vlocity_namespace%__AttributeCategory__c/MntlHlthOutptProf",
            "VlocityRecordSObjectType": "%vlocity_namespace%__AttributeCategory__c"
        },
        "%vlocity_namespace%__AttributeCategoryName__c": "Mental Health - Outpatient Professional",
        "%vlocity_namespace%__AttributeGroupType__c": "",
        "%vlocity_namespace%__Code__c": "MntlHlthOutptProf_Instrctn3",
        "%vlocity_namespace%__Configurable__c": true,
        "%vlocity_namespace%__CustomConfigUiTemplate__c": "",
        "%vlocity_namespace%__Description__c": "",
        "%vlocity_namespace%__DisplaySequence__c": 13,
        "%vlocity_namespace%__EffectiveFromDate__c": "",
        "%vlocity_namespace%__EffectiveUntilDate__c": "",
        "%vlocity_namespace%__Filterable__c": true,
        "%vlocity_namespace%__GlobalKey__c": "1e3d437b-7745-dda0-ea23-d5743bfb9e74",
        "%vlocity_namespace%__HelpText__c": "",
        "%vlocity_namespace%__IsCloneable__c": true,
        "%vlocity_namespace%__IsEncrypted__c": false,
        "%vlocity_namespace%__IsNotAssetizable__c": false,
        "%vlocity_namespace%__IsPrivate__c": false,
        "%vlocity_namespace%__OwnerId__c": "",
        "%vlocity_namespace%__PicklistId__c": "",
        "%vlocity_namespace%__UniqueNameField__c": "",
        "%vlocity_namespace%__ValueType__c": "Text",
        "%vlocity_namespace%__Value__c": "",
        "%vlocity_namespace%__isDefaultHidden__c": false,
        "Name": "Instruction",
        "VlocityDataPackType": "SObject",
        "VlocityRecordSObjectType": "%vlocity_namespace%__Attribute__c",
        "VlocityRecordSourceKey": "%vlocity_namespace%__Attribute__c/MntlHlthOutptProf_Instrctn3"
    },
    {
        "%vlocity_namespace%__ActiveFlg__c": true,
        "%vlocity_namespace%__AttributeCategoryCode__c": "MntlHlthOutptProf",
        "%vlocity_namespace%__AttributeCategoryId__c": {
            "%vlocity_namespace%__Code__c": "MntlHlthOutptProf",
            "VlocityDataPackType": "VlocityMatchingKeyObject",
            "VlocityMatchingRecordSourceKey": "%vlocity_namespace%__AttributeCategory__c/MntlHlthOutptProf",
            "VlocityRecordSObjectType": "%vlocity_namespace%__AttributeCategory__c"
        },
        "%vlocity_namespace%__AttributeCategoryName__c": "Mental Health - Outpatient Professional",
        "%vlocity_namespace%__AttributeGroupType__c": "In-Network",
        "%vlocity_namespace%__Code__c": "MntlHlthOutptProf_covered_inn",
        "%vlocity_namespace%__Configurable__c": true,
        "%vlocity_namespace%__CustomConfigUiTemplate__c": "",
        "%vlocity_namespace%__Description__c": "",
        "%vlocity_namespace%__DisplaySequence__c": 10,
        "%vlocity_namespace%__EffectiveFromDate__c": "",
        "%vlocity_namespace%__EffectiveUntilDate__c": "",
        "%vlocity_namespace%__Filterable__c": true,
        "%vlocity_namespace%__GlobalKey__c": "46fff406-a78b-cab5-a3a2-fa5bd2b8974b",
        "%vlocity_namespace%__HelpText__c": "",
        "%vlocity_namespace%__IsCloneable__c": true,
        "%vlocity_namespace%__IsEncrypted__c": false,
        "%vlocity_namespace%__IsNotAssetizable__c": false,
        "%vlocity_namespace%__IsPrivate__c": false,
        "%vlocity_namespace%__OwnerId__c": "",
        "%vlocity_namespace%__PicklistId__c": "",
        "%vlocity_namespace%__UniqueNameField__c": "",
        "%vlocity_namespace%__ValueType__c": "Text",
        "%vlocity_namespace%__Value__c": "",
        "%vlocity_namespace%__isDefaultHidden__c": false,
        "Name": "Covered",
        "VlocityDataPackType": "SObject",
        "VlocityRecordSObjectType": "%vlocity_namespace%__Attribute__c",
        "VlocityRecordSourceKey": "%vlocity_namespace%__Attribute__c/MntlHlthOutptProf_covered_inn"
    },
    {
        "%vlocity_namespace%__ActiveFlg__c": true,
        "%vlocity_namespace%__AttributeCategoryCode__c": "MntlHlthOutptProf",
        "%vlocity_namespace%__AttributeCategoryId__c": {
            "%vlocity_namespace%__Code__c": "MntlHlthOutptProf",
            "VlocityDataPackType": "VlocityMatchingKeyObject",
            "VlocityMatchingRecordSourceKey": "%vlocity_namespace%__AttributeCategory__c/MntlHlthOutptProf",
            "VlocityRecordSObjectType": "%vlocity_namespace%__AttributeCategory__c"
        },
        "%vlocity_namespace%__AttributeCategoryName__c": "Mental Health - Outpatient Professional",
        "%vlocity_namespace%__AttributeGroupType__c": "Out-Of-Network",
        "%vlocity_namespace%__Code__c": "MntlHlthOutptProf_covered_oon",
        "%vlocity_namespace%__Configurable__c": true,
        "%vlocity_namespace%__CustomConfigUiTemplate__c": "",
        "%vlocity_namespace%__Description__c": "",
        "%vlocity_namespace%__DisplaySequence__c": 50,
        "%vlocity_namespace%__EffectiveFromDate__c": "",
        "%vlocity_namespace%__EffectiveUntilDate__c": "",
        "%vlocity_namespace%__Filterable__c": true,
        "%vlocity_namespace%__GlobalKey__c": "0427b702-ec51-3dcf-8d13-50c861674a9b",
        "%vlocity_namespace%__HelpText__c": "",
        "%vlocity_namespace%__IsCloneable__c": true,
        "%vlocity_namespace%__IsEncrypted__c": false,
        "%vlocity_namespace%__IsNotAssetizable__c": false,
        "%vlocity_namespace%__IsPrivate__c": false,
        "%vlocity_namespace%__OwnerId__c": "",
        "%vlocity_namespace%__PicklistId__c": "",
        "%vlocity_namespace%__UniqueNameField__c": "",
        "%vlocity_namespace%__ValueType__c": "Text",
        "%vlocity_namespace%__Value__c": "",
        "%vlocity_namespace%__isDefaultHidden__c": false,
        "Name": "Covered",
        "VlocityDataPackType": "SObject",
        "VlocityRecordSObjectType": "%vlocity_namespace%__Attribute__c",
        "VlocityRecordSourceKey": "%vlocity_namespace%__Attribute__c/MntlHlthOutptProf_covered_oon"
    }
]